neurovis/__init__.py
neurovis/neurovis.py
neurovis-0.1.0.dist-info/DESCRIPTION.rst
neurovis-0.1.0.dist-info/METADATA
neurovis-0.1.0.dist-info/RECORD
neurovis-0.1.0.dist-info/WHEEL
neurovis-0.1.0.dist-info/metadata.json
neurovis-0.1.0.dist-info/top_level.txt
