Metadata-Version: 2.0
Name: neurovis
Version: 0.1.0
Summary: visualization modules for neuroimaging data
Home-page: https://github.com/raamana/neurovis
Author: Pradeep Reddy Raamana
Author-email: raamana@gmail.com
License: Apache Software License 2.0
Keywords: neurovis
Platform: UNKNOWN
Classifier: Development Status :: 2 - Pre-Alpha
Classifier: Intended Audience :: Developers
Classifier: License :: OSI Approved :: Apache Software License
Classifier: Natural Language :: English
Classifier: Programming Language :: Python :: 2
Classifier: Programming Language :: Python :: 2.7
Classifier: Programming Language :: Python :: 3
Classifier: Programming Language :: Python :: 3.4
Classifier: Programming Language :: Python :: 3.5
Classifier: Programming Language :: Python :: 3.6
